femr/__init__.py
femr/_version.py
femr/ontology.py
femr/pat_utils.py
femr/py.typed
femr/splits.py
femr/stat_utils.py
femr/featurizers/__init__.py
femr/featurizers/core.py
femr/featurizers/featurizers.py
femr/featurizers/utils.py
femr/labelers/__init__.py
femr/labelers/core.py
femr/labelers/omop.py
femr/models/config.py
femr/models/processor.py
femr/models/rmsnorm.py
femr/models/tasks.py
femr/models/transformer.py
femr/models/xformers.py
femr/models/tokenizer/__init__.py
femr/models/tokenizer/flat_tokenizer.py
femr/models/tokenizer/hierarchical_tokenizer.py
femr/post_etl_pipelines/__init__.py
femr/post_etl_pipelines/stanford.py
femr/transforms/__init__.py
femr/transforms/stanford.py
femr-0.2.4.dist-info/licenses/LICENSE
femr-0.2.4.dist-info/METADATA
femr-0.2.4.dist-info/WHEEL
femr-0.2.4.dist-info/entry_points.txt
femr-0.2.4.dist-info/top_level.txt
femr-0.2.4.dist-info/RECORD
