Metadata-Version: 2.4
Name: femr
Version: 0.2.4
Summary: Framework for Electronic Medical Records. A python package for building models using EHR data.
Requires-Python: >3.9
License-File: LICENSE
Requires-Dist: numpy>=1.22
Requires-Dist: scipy>=1.6
Requires-Dist: scikit-learn>=0.24
Requires-Dist: tqdm>=4.60.0
Requires-Dist: zstandard>=0.18
Requires-Dist: icecream==2.1.3
Requires-Dist: nptyping==2.4.1
Requires-Dist: msgpack>=1.0.5
Requires-Dist: meds==0.3.3
Requires-Dist: meds_reader>=0.1.3
Requires-Dist: torch>=2.1.2
Requires-Dist: transformers>=4.25
Requires-Dist: datasets>=2.15
Requires-Dist: polars>=0.20
Requires-Dist: dill>=0.3.7
Requires-Dist: pandas>=2.2
Requires-Dist: pandas-stubs>=2.2
Requires-Dist: types-tqdm>=4.60.0
Requires-Dist: xformers>=0.0.28
Requires-Dist: torch_hawk
Requires-Dist: accelerate>=0.26.0
Provides-Extra: build
Requires-Dist: pytest>=5.2; extra == "build"
Requires-Dist: flake8-future-import>=0.4.6; extra == "build"
Requires-Dist: black>=19.10b0; extra == "build"
Requires-Dist: isort>=5.3.2; extra == "build"
Requires-Dist: mypy>=0.782; extra == "build"
Requires-Dist: flake8>=3.8.3; extra == "build"
Requires-Dist: sphinx>=3.2.1; extra == "build"
Requires-Dist: sphinx-rtd-theme>=0.5.0; extra == "build"
Requires-Dist: sphinx-autoapi>=1.5.1; extra == "build"
Requires-Dist: torchtyping==0.1.4; extra == "build"
Dynamic: license-file
